pytivo/__init__.py
pytivo/keycodes.json
pytivo/tivo_client.py
pytivo-0.0.2.dist-info/LICENSE
pytivo-0.0.2.dist-info/METADATA
pytivo-0.0.2.dist-info/WHEEL
pytivo-0.0.2.dist-info/top_level.txt
pytivo-0.0.2.dist-info/RECORD
