Metadata-Version: 2.1
Name: pytivo
Version: 0.0.2
Summary: Library To Control TiVo Devices
Home-page: https://github.com/bfayers/pytivo
Author: Ben Fayers
Author-email: ben.fayers@gmail.com
License: UNKNOWN
Download-URL: https://github.com/bfayers/pytivo/archive/0.0.1.tar.gz
Keywords: tivo,pytivo,control
Platform: UNKNOWN
